crawler4py/__init__.py
crawler4py/command.py
crawler4py/crawler.py
crawler4py/log.py
crawler4py/manager.py
crawler4py/setting.py
crawler4py/setup.py
crawler4py/test.py
crawler4py/dispatch/__init__.py
crawler4py/dispatch/dispatch.py
crawler4py/dispatch/monitor.py
crawler4py/dispatch/starter.py
crawler4py/download/__init__.py
crawler4py/download/base_download.py
crawler4py/download/downloader.py
crawler4py/download/process.py
crawler4py/download/request.py
crawler4py/extractor/__init__.py
crawler4py/extractor/analysis.py
crawler4py/extractor/base_extract.py
crawler4py/extractor/extractor.py
crawler4py/storage_dup/__init__.py
crawler4py/storage_dup/base_storage_dup.py
crawler4py/storage_dup/storage_dup.py
crawler4py/util/__init__.py
crawler4py/util/commonutil.py
crawler4py/util/mongoutil.py
crawler4py/util/rabbitmqutil.py
crawler4py/util/redisutil.py
crawler4py/util/running_params.py
crawler4py/util/sqlutil.py
crawler4py-0.5.dist-info/LICENSE
crawler4py-0.5.dist-info/METADATA
crawler4py-0.5.dist-info/WHEEL
crawler4py-0.5.dist-info/entry_points.txt
crawler4py-0.5.dist-info/top_level.txt
crawler4py-0.5.dist-info/RECORD
